StatisticalLearningTheoryNotesStanfordCs229tStat231/README.md
StatisticalLearningTheoryNotesStanfordCs229tStat231/__init__.py
StatisticalLearningTheoryNotesStanfordCs229tStat231/__main__.py
StatisticalLearningTheoryNotesStanfordCs229tStat231/file.pdf
StatisticalLearningTheoryNotesStanfordCs229tStat231/index.html
statistical_learning_theory_notes_stanford_cs229t_stat231-2024.3.4.0.dist-info/METADATA
statistical_learning_theory_notes_stanford_cs229t_stat231-2024.3.4.0.dist-info/WHEEL
statistical_learning_theory_notes_stanford_cs229t_stat231-2024.3.4.0.dist-info/entry_points.txt
statistical_learning_theory_notes_stanford_cs229t_stat231-2024.3.4.0.dist-info/top_level.txt
statistical_learning_theory_notes_stanford_cs229t_stat231-2024.3.4.0.dist-info/RECORD
